{
  "project_info": {
    "project_number": "894597129282",
    "firebase_url": "https://trackingandalarmsystem-ea828.firebaseio.com",
    "project_id": "trackingandalarmsystem-ea828",
    "storage_bucket": "trackingandalarmsystem-ea828.appspot.com"
  },
  "client": [
    {
      "client_info": {
        "mobilesdk_app_id": "1:894597129282:android:6f99465fb3cb7a7f2679db",
        "android_client_info": {
          "package_name": "com.pawanrawee.myapp"
        }
      },
      "oauth_client": [
        {
          "client_id": "894597129282-omrjd8v795prgu3c0oovr96j0j1bm077.apps.googleusercontent.com",
          "client_type": 3
        }
      ],
      "api_key": [
        {
          "current_key": "AIzaSyDJZANS1pwPhbtgCwdNKXpv4BX_bDMPTF8"
        }
      ],
      "services": {
        "appinvite_service": {
          "other_platform_oauth_client": [
            {
              "client_id": "894597129282-omrjd8v795prgu3c0oovr96j0j1bm077.apps.googleusercontent.com",
              "client_type": 3
            }
          ]
        }
      }
    }
  ],
  "configuration_version": "1"
}